{
  "project_info": {
    "project_number": "537281031154",
    "project_id": "e-commerce-ab702",
    "storage_bucket": "e-commerce-ab702.firebasestorage.app"
  },
  "client": [
    {
      "client_info": {
        "mobilesdk_app_id": "1:537281031154:android:1774aea7bbc445438a196b",
        "android_client_info": {
          "package_name": "com.example.e_commerce"
        }
      },
      "oauth_client": [],
      "api_key": [
        {
          "current_key": "AIzaSyCF8S4BiIcQ54juuMIXeH1PzYMO_kqVSeo"
        }
      ],
      "services": {
        "appinvite_service": {
          "other_platform_oauth_client": []
        }
      }
    }
  ],
  "configuration_version": "1"
}